edx_when/__init__.py
edx_when/admin.py
edx_when/api.py
edx_when/apps.py
edx_when/field_data.py
edx_when/models.py
edx_when/urls.py
edx_when/utils.py
edx_when/views.py
edx_when/migrations/0001_initial.py
edx_when/migrations/0002_auto_20190318_1736.py
edx_when/migrations/0003_auto_20190402_1501.py
edx_when/migrations/0004_datepolicy_rel_date.py
edx_when/migrations/0005_auto_20190911_1056.py
edx_when/migrations/0006_drop_active_index.py
edx_when/migrations/0007_meta_tweaks.py
edx_when/migrations/0008_courseversion_block_type.py
edx_when/migrations/__init__.py
edx_when/templates/edx_schedule/base.html
edx_when-3.1.0.dist-info/licenses/AUTHORS
edx_when-3.1.0.dist-info/licenses/LICENSE.txt
edx_when-3.1.0.dist-info/METADATA
edx_when-3.1.0.dist-info/WHEEL
edx_when-3.1.0.dist-info/entry_points.txt
edx_when-3.1.0.dist-info/top_level.txt
edx_when-3.1.0.dist-info/RECORD
