Metadata-Version: 2.4
Name: edx-when
Version: 3.1.0
Summary: Your project description goes here
Home-page: https://github.com/openedx/edx-when
Author: edX
Author-email: oscm@edx.org
License: AGPL 3.0
Keywords: Django edx
Classifier: Development Status :: 3 - Alpha
Classifier: Framework :: Django
Classifier: Framework :: Django :: 4.2
Classifier: Intended Audience :: Developers
Classifier: License :: OSI Approved :: GNU Affero General Public License v3 or later (AGPLv3+)
Classifier: Natural Language :: English
Classifier: Programming Language :: Python :: 3
Classifier: Programming Language :: Python :: 3.11
Classifier: Programming Language :: Python :: 3.12
License-File: LICENSE.txt
License-File: AUTHORS
Requires-Dist: Django>=1.11
Requires-Dist: django-model-utils
Requires-Dist: edx-django-utils
Requires-Dist: edx-drf-extensions
Requires-Dist: edx-opaque-keys
Requires-Dist: xblock
Dynamic: author
Dynamic: author-email
Dynamic: classifier
Dynamic: description
Dynamic: description-content-type
Dynamic: home-page
Dynamic: keywords
Dynamic: license
Dynamic: license-file
Dynamic: requires-dist
Dynamic: summary
